mrglang/__init__.py
mrglang/cli.py
mrglang-2.0.0.dist-info/licenses/LICENSE
mrglang-2.0.0.dist-info/METADATA
mrglang-2.0.0.dist-info/WHEEL
mrglang-2.0.0.dist-info/entry_points.txt
mrglang-2.0.0.dist-info/top_level.txt
mrglang-2.0.0.dist-info/RECORD
